[
	{
		"key": "group_6508afd67d90a",
		"title": "Choctaw Events Taxonomy — Venues",
		"fields": [
			{
				"key": "field_650b16d7ea4b3",
				"label": "Venue Information",
				"name": "venue_information",
				"aria-label": "",
				"type": "group",
				"instructions": "",
				"required": 0,
				"conditional_logic": 0,
				"wrapper": {
					"width": "",
					"class": "",
					"id": ""
				},
				"relevanssi_exclude": 0,
				"layout": "block",
				"sub_fields": [
					{
						"key": "field_650b170aea4b4",
						"label": "Street Address",
						"name": "street_address",
						"aria-label": "",
						"type": "text",
						"instructions": "",
						"required": 1,
						"conditional_logic": 0,
						"wrapper": {
							"width": "",
							"class": "",
							"id": ""
						},
						"relevanssi_exclude": 0,
						"default_value": "",
						"maxlength": "",
						"placeholder": "",
						"prepend": "",
						"append": ""
					},
					{
						"key": "field_650b1720ea4b5",
						"label": "City",
						"name": "city",
						"aria-label": "",
						"type": "text",
						"instructions": "",
						"required": 1,
						"conditional_logic": 0,
						"wrapper": {
							"width": "",
							"class": "",
							"id": ""
						},
						"relevanssi_exclude": 0,
						"default_value": "",
						"maxlength": "",
						"placeholder": "",
						"prepend": "",
						"append": ""
					},
					{
						"key": "field_650b1730ea4b6",
						"label": "State",
						"name": "state",
						"aria-label": "",
						"type": "select",
						"instructions": "",
						"required": 1,
						"conditional_logic": 0,
						"wrapper": {
							"width": "",
							"class": "",
							"id": ""
						},
						"relevanssi_exclude": 0,
						"choices": {
							"Oklahoma": "Oklahoma",
							"Alabama": "Alabama",
							"Alaska": "Alaska",
							"Arizona": "Arizona",
							"Arkansas": "Arkansas",
							"California": "California",
							"Colorado": "Colorado",
							"Connecticut": "Connecticut",
							"Delaware": "Delaware",
							"Florida": "Florida",
							"Georgia": "Georgia",
							"Hawaii": "Hawaii",
							"Idaho": "Idaho",
							"Illinois": "Illinois",
							"Indiana": "Indiana",
							"Iowa": "Iowa",
							"Kansas": "Kansas",
							"Kentucky": "Kentucky",
							"Louisiana": "Louisiana",
							"Maine": "Maine",
							"Maryland": "Maryland",
							"Massachusetts": "Massachusetts",
							"Michigan": "Michigan",
							"Minnesota": "Minnesota",
							"Mississippi": "Mississippi",
							"Missouri": "Missouri",
							"Montana": "Montana",
							"Nebraska": "Nebraska",
							"Nevada": "Nevada",
							"New Hampshire": "New Hampshire",
							"New Jersey": "New Jersey",
							"New Mexico": "New Mexico",
							"New York": "New York",
							"North Carolina": "North Carolina",
							"North Dakota": "North Dakota",
							"Ohio": "Ohio",
							"Oregon": "Oregon",
							"Pennsylvania": "Pennsylvania",
							"Rhode Island": "Rhode Island",
							"South Carolina": "South Carolina",
							"South Dakota": "South Dakota",
							"Tennessee": "Tennessee",
							"Texas": "Texas",
							"Utah": "Utah",
							"Vermont": "Vermont",
							"Virginia": "Virginia",
							"Washington": "Washington",
							"West Virginia": "West Virginia",
							"Wisconsin": "Wisconsin",
							"Wyoming": "Wyoming"
						},
						"default_value": "Oklahoma",
						"return_format": "value",
						"multiple": 0,
						"allow_null": 0,
						"ui": 0,
						"ajax": 0,
						"placeholder": ""
					},
					{
						"key": "field_650b181aea4b7",
						"label": "Zip Code",
						"name": "zip_code",
						"aria-label": "",
						"type": "number",
						"instructions": "",
						"required": 1,
						"conditional_logic": 0,
						"wrapper": {
							"width": "",
							"class": "",
							"id": ""
						},
						"relevanssi_exclude": 0,
						"default_value": "",
						"min": "",
						"max": "",
						"placeholder": "",
						"step": "",
						"prepend": "",
						"append": ""
					},
					{
						"key": "field_650b182cea4b8",
						"label": "Phone",
						"name": "phone",
						"aria-label": "",
						"type": "text",
						"instructions": "",
						"required": 0,
						"conditional_logic": 0,
						"wrapper": {
							"width": "",
							"class": "",
							"id": ""
						},
						"relevanssi_exclude": 0,
						"default_value": "",
						"maxlength": "",
						"placeholder": "",
						"prepend": "",
						"append": ""
					},
					{
						"key": "field_650b183bea4b9",
						"label": "Website",
						"name": "website",
						"aria-label": "",
						"type": "url",
						"instructions": "",
						"required": 0,
						"conditional_logic": 0,
						"wrapper": {
							"width": "",
							"class": "",
							"id": ""
						},
						"relevanssi_exclude": 0,
						"default_value": "",
						"placeholder": ""
					},
					{
						"key": "field_650b183bea4c0",
						"label": "Direction Url",
						"name": "direction_url",
						"aria-label": "",
						"type": "url",
						"instructions": "",
						"required": 1,
						"conditional_logic": 0,
						"wrapper": {
							"width": "",
							"class": "",
							"id": ""
						},
						"relevanssi_exclude": 0,
						"default_value": "",
						"placeholder": ""
					}
				]
			}
		],
		"location": [
			[
				{
					"param": "taxonomy",
					"operator": "==",
					"value": "choctaw-events-venue"
				}
			]
		],
		"menu_order": 0,
		"position": "normal",
		"style": "default",
		"label_placement": "top",
		"instruction_placement": "label",
		"hide_on_screen": "",
		"active": true,
		"description": "",
		"show_in_rest": 1
	},
	{
		"key": "taxonomy_650b1468966c9",
		"title": "Venues",
		"menu_order": 0,
		"active": true,
		"taxonomy": "choctaw-events-venue",
		"object_type": [
			"choctaw-events"
		],
		"advanced_configuration": 1,
		"import_source": "",
		"import_date": "",
		"labels": {
			"name": "Venues",
			"singular_name": "Venue",
			"menu_name": "Venues",
			"all_items": "All Venues",
			"edit_item": "Edit Venue",
			"view_item": "View Venue",
			"update_item": "Update Venue",
			"add_new_item": "Add New Venue",
			"new_item_name": "New Venue Name",
			"parent_item": "Parent Venue",
			"parent_item_colon": "Parent Venue:",
			"search_items": "Search Venues",
			"most_used": "",
			"not_found": "No venues found",
			"no_terms": "No venues",
			"name_field_description": "",
			"slug_field_description": "",
			"parent_field_description": "",
			"desc_field_description": "",
			"filter_by_item": "Filter by venue",
			"items_list_navigation": "Venues list navigation",
			"items_list": "Venues list",
			"back_to_items": "← Go to venues",
			"item_link": "Venue Link",
			"item_link_description": "A link to a venue"
		},
		"description": "",
		"capabilities": {
			"manage_terms": "manage_categories",
			"edit_terms": "manage_categories",
			"delete_terms": "manage_categories",
			"assign_terms": "edit_posts"
		},
		"public": 1,
		"publicly_queryable": 1,
		"hierarchical": 1,
		"show_ui": 1,
		"show_in_menu": 1,
		"show_in_nav_menus": 0,
		"show_in_rest": 1,
		"rest_base": "",
		"rest_namespace": "wp\/v2",
		"rest_controller_class": "WP_REST_Terms_Controller",
		"show_tagcloud": 0,
		"show_in_quick_edit": 1,
		"show_admin_column": 1,
		"rewrite": {
			"permalink_rewrite": "custom_permalink",
			"slug": "venue",
			"with_front": "1",
			"rewrite_hierarchical": "1"
		},
		"query_var": "post_type_key",
		"query_var_name": "",
		"default_term": {
			"default_term_enabled": "0"
		},
		"sort": 0,
		"meta_box": "default",
		"meta_box_cb": "",
		"meta_box_sanitize_cb": ""
	}
]
